[
  {
    "username": "Lord Ernesto",
    "email": "ernestogambelarghe@gmail.com",
    "password": "$2b$10$BtNonzw7itBwX3qGMkWAk.RJYeoCOMHPl2LQuj62TLDc2qeB8Y.uW",
    "googleId": null,
    "avatar": "dragon",
    "puntiRankiard": 0,
    "isAdmin": false,
    "resetPasswordToken": null,
    "resetPasswordExpires": null,
    "id": 1,
    "createdAt": "2026-02-28T13:42:40.852Z"
  },
  {
    "username": "Danny Spaccachiodi",
    "email": "mircomartello1@gmail.com",
    "password": "$2b$10$tu2gN9hptML41ZScWD6ltuOkzk9yg/FugFjP.gLjR57kD57ofAJtK",
    "googleId": null,
    "avatar": "lightning",
    "puntiRankiard": 0,
    "isAdmin": false,
    "resetPasswordToken": null,
    "resetPasswordExpires": null,
    "id": 2,
    "createdAt": "2026-03-06T20:45:15.264Z"
  },
  {
    "username": "Gino87",
    "email": "ginocontapassi@gmail.com",
    "password": "$2b$10$M/da2m211C7IomTn.PJQmuzNNfpdXK22h.jkzNq0vDhrvgfu588Vi",
    "googleId": null,
    "avatar": "fox",
    "puntiRankiard": 0,
    "isAdmin": false,
    "resetPasswordToken": null,
    "resetPasswordExpires": null,
    "id": 3,
    "createdAt": "2026-03-06T20:57:31.828Z"
  }
]